{
  "db_name": "PostgreSQL",
  "query": "SELECT id, name FROM media.tv_shows\n           WHERE meta_status = 'pending_meta'\n           ORDER BY created_at DESC\n           LIMIT 10",
  "describe": {
    "columns": [
      {
        "ordinal": 0,
        "name": "id",
        "type_info": "Uuid"
      },
      {
        "ordinal": 1,
        "name": "name",
        "type_info": "Varchar"
      }
    ],
    "parameters": {
      "Left": []
    },
    "nullable": [
      false,
      false
    ]
  },
  "hash": "06a12ad6d02a676de5650b73b416f5931599cce31e99bf5b882a7b800a107e33"
}
